lumberkid/__init__.py
lumberkid/__main__.py
lumberkid/commands.py
lumberkid/config.py
lumberkid/subprocess_utils.py
lumberkid/test_config.py
lumberkid/ui.py
lumberkid/forge/forge.py
lumberkid/forge/github_forge.py
lumberkid/issue_provider/github_provider.py
lumberkid/issue_provider/issue_provider.py
lumberkid/issue_provider/issues.py
lumberkid/vcs/git_vcs.py
lumberkid/vcs/test_git.py
lumberkid/vcs/vcs.py
lumberkid-0.3.0.dist-info/LICENSE
lumberkid-0.3.0.dist-info/METADATA
lumberkid-0.3.0.dist-info/WHEEL
lumberkid-0.3.0.dist-info/entry_points.txt
lumberkid-0.3.0.dist-info/top_level.txt
lumberkid-0.3.0.dist-info/RECORD
