Metadata-Version: 2.1
Name: lumberkid
Version: 0.3.0
Summary: lumberkid
License: MIT License
Project-URL: homepage, https://github.com/MartinBernstorff/lumberkid
Project-URL: repository, https://github.com/MartinBernstorff/lumberkid
Project-URL: documentation, https://MartinBernstorff.github.io/lumberkid/
Classifier: Programming Language :: Python :: 3.10
Requires-Python: >=3.10
License-File: LICENSE
Requires-Dist: typer>=0.12.3
Requires-Dist: iterfzf>=1.4.0.51.0
Requires-Dist: pydantic>=2.8.2
Requires-Dist: tomli-w>=1.0.0
Requires-Dist: toml>=0.10.2
